runmanager/__init__.py
runmanager/__main__.py
runmanager/__version__.py
runmanager/batch_compiler.py
runmanager/desktop-app.json
runmanager/functions.py
runmanager/globals_diff.bat
runmanager/globals_diff.py
runmanager/group.ui
runmanager/main.ui
runmanager/remote.py
runmanager/runmanager.ico
runmanager/runmanager.svg
runmanager-3.3.0.dist-info/licenses/LICENSE.txt
runmanager-3.3.0.dist-info/METADATA
runmanager-3.3.0.dist-info/WHEEL
runmanager-3.3.0.dist-info/entry_points.txt
runmanager-3.3.0.dist-info/top_level.txt
runmanager-3.3.0.dist-info/RECORD
