Metadata-Version: 2.4
Name: runmanager
Version: 3.3.0
Summary: Graphical control of parameterised experiments composed in labscript
Author-email: The labscript suite community <labscriptsuite@googlegroups.com>
License: Copyright (c) 2013, Monash University
Project-URL: Homepage, http://labscriptsuite.org/
Project-URL: Documentation, https://docs.labscriptsuite.org/
Project-URL: Repository, https://github.com/labscript-suite/runmanager/
Project-URL: Downloads, https://github.com/labscript-suite/runmanager/releases/
Project-URL: Tracker, https://github.com/labscript-suite/runmanager/issues/
Keywords: experiment control,automation
Classifier: License :: OSI Approved :: BSD License
Classifier: Programming Language :: Python :: 3 :: Only
Requires-Python: >=3.8
License-File: LICENSE.txt
Requires-Dist: desktop-app>=0.1.2
Requires-Dist: labscript>=3.0.0
Requires-Dist: labscript_utils>=3.3.0
Requires-Dist: pandas>=0.13
Requires-Dist: qtutils>=2.2.2
Requires-Dist: matplotlib
Provides-Extra: docs
Requires-Dist: PyQt5; extra == "docs"
Requires-Dist: Sphinx==8.2.3; extra == "docs"
Requires-Dist: sphinx-rtd-theme==3.0.2; extra == "docs"
Requires-Dist: myst_parser==4.0.1; extra == "docs"
Dynamic: license-file
